README.md
setup.py
pyimgaug3d/__init__.py
pyimgaug3d.egg-info/PKG-INFO
pyimgaug3d.egg-info/SOURCES.txt
pyimgaug3d.egg-info/dependency_links.txt
pyimgaug3d.egg-info/requires.txt
pyimgaug3d.egg-info/top_level.txt
pyimgaug3d/augmentation/__init__.py
pyimgaug3d/augmentation/src/__init__.py
pyimgaug3d/augmentation/src/base_augmentation.py
pyimgaug3d/augmentation/src/flip_augmentation.py
pyimgaug3d/augmentation/src/identity.py
pyimgaug3d/augmentation/src/warp.py
pyimgaug3d/augmenters/__init__.py
pyimgaug3d/augmenters/src/__init__.py
pyimgaug3d/augmenters/src/base_augmenter.py
pyimgaug3d/augmenters/src/img_seg_augmenter.py
pyimgaug3d/preprocess/__init__.py
pyimgaug3d/preprocess/src/__init__.py
pyimgaug3d/utils/__init__.py
pyimgaug3d/utils/src/__init__.py
pyimgaug3d/utils/src/array_ops.py
pyimgaug3d/utils/src/debug.py