Metadata-Version: 2.1
Name: pyimgaug3d
Version: 0.43
Summary: Python image augmentation
Home-page: UNKNOWN
Author: Siyu Liu
Author-email: siyu.liu2@uqconnect.edu.au
License: UNKNOWN
Platform: UNKNOWN
Classifier: Programming Language :: Python :: 3
Classifier: License :: OSI Approved :: MIT License
Classifier: Operating System :: OS Independent
Requires-Python: >=3.5, <4
